llm_moonshot.py
llm_moonshot-0.3.1.dist-info/METADATA
llm_moonshot-0.3.1.dist-info/WHEEL
llm_moonshot-0.3.1.dist-info/entry_points.txt
llm_moonshot-0.3.1.dist-info/top_level.txt
llm_moonshot-0.3.1.dist-info/RECORD
