Metadata-Version: 2.4
Name: llm-moonshot
Version: 0.3.1
Summary: Run prompts against LLMs hosted by Moonshot
Author: NickMystic
Project-URL: Homepage, https://github.com/ghostofpokemon/llm-moonshot
Project-URL: Repository, https://github.com/ghostofpokemon/llm-moonshot
Project-URL: Changelog, https://github.com/ghostofpokemon/llm-moonshot/releases
Project-URL: Issues, https://github.com/ghostofpokemon/llm-moonshot/issues
Classifier: License :: OSI Approved :: Apache Software License
Requires-Python: >=3.9
Requires-Dist: llm>=0.22
Requires-Dist: httpx
Requires-Dist: httpx-sse
Requires-Dist: rich>=13.0
Provides-Extra: test
Requires-Dist: pytest; extra == "test"
Requires-Dist: pytest-httpx; extra == "test"
Requires-Dist: pytest-asyncio; extra == "test"
